Workbook

Sheet RESUMO FATURAMENTO
C1: PREFEITURA MUNICIPAL DE DOM AQUINO/MT
C3: TERMO DE PARCERIA Nº 001/2026
C4: SECRETARIA MUNICIPAL DE SAÚDE
C5: TERMO DE PARCERIA Nº 001/2026
A7: RELATÓRIO SINTÉTICO FATURAMENTO - PJ
A9: OSCIP. ORGANIZAÇÃO DE SAÚDE SÃO BENTO
A11: PROJETO FORSAÚDE – Fortalecimento da Saúde Pública Municipal
A13: PERÍODO. AGOSTO DE 2026
A15: COMPETÊNCIA. 01 A 31 DE AGOSTO DE 2026
A19: 1 - EXECUÇÃO DIRETA DO PROJETO | H19: =SUM(H20:J23) -> 679761.46
A20: 1.1 - CLT | H20: 0
A21: 1.2 - PJ | G21: % | H21: =SUM(H22:J23) -> 339880.73
B22: Secretaria de Saúde - APS/PAB | G22: =H22/$H$21 -> 0.48889933 | H22: =SUMIFS('DETALHAMENTO PJ SAUDE'!L:L,'DETALHAMENTO PJ SAUDE'!E:E,'RESUMO FATURAMENTO'!B22) -> 166167.46
B23: Secretaria de Saúde - MAC | G23: =H23/$H$21 -> 0.51110067 | H23: =SUMIFS('DETALHAMENTO PJ SAUDE'!L:L,'DETALHAMENTO PJ SAUDE'!E:E,'RESUMO FATURAMENTO'!B23) -> 173713.27
A24: 2 - DESPESAS ADMINISTRATIVAS E OPERACIONAIS | H24: ='DESPESA ADM'!J27 -> 49146.183
B25: Secretaria de Saúde - APS/PAB | H25: =$H$24*G22 -> 24027.536
B26: Secretaria de Saúde - MAC | H26: =$H$24*G23 -> 25118.647
A27: TOTAL | H27: =H19+H24 -> 728907.65
A33: DOM AQUINO/MT, 08 DE SETEMBRO DE 2026.
C40: IREDIR MARIA LACCAL DA SILVA FERREIRA
C41: PRESIDENTE

Sheet DETALHAMENTO CLT
A2: ='RESUMO FATURAMENTO'!C1 -> PREFEITURA MUNICIPAL DE DOM AQUINO/MT
A3: ='RESUMO FATURAMENTO'!C3 -> TERMO DE PARCERIA Nº 001/2026
A4: ='RESUMO FATURAMENTO'!C4 -> SECRETARIA MUNICIPAL DE SAÚDE
A6: ='RESUMO FATURAMENTO'!A20 -> 1.1 - CLT
A8: ='RESUMO FATURAMENTO'!A9 -> OSCIP. ORGANIZAÇÃO DE SAÚDE SÃO BENTO | G8: ÓRGÃO PARCEIRO: PREFEITURA MUNICIPAL DE DOM AQUINO/MT
A10: ='RESUMO FATURAMENTO'!C4 -> SECRETARIA MUNICIPAL DE SAÚDE | G10: ='RESUMO FATURAMENTO'!A11 -> PROJETO FORSAÚDE – Fortalecimento da Saúde Pública Municipal
A12: ='RESUMO FATURAMENTO'!A15 -> COMPETÊNCIA. 01 A 31 DE AGOSTO DE 2026
A13: Codigo Consisa | B13: Colaborador | C13: CPF | D13: Cargo | E13: Setor | F13: Situação | G13: Remuneração Base | H13: Ref | I13: Remuneração | J13: Insalubridade | K13: Periculosidade | L13: Salário Família | M13: Horas Extras | N13: Complemento Piso Enfermagem | O13: DSR | P13: Adicional Noturno | Q13: Gratificação | R13: Plantão | S13: Faltas | T13: Proventos | U13: Provisão 19,44% | V13: Verbas Rescisórias | W13: Multa 40% | X13: Encargos Tributários | Y13: Valor Total
A14: 391 | B14: Aline De Oliveira Vergilio | C14: 030.378.821-66 | D14: Tecnico De Enfermagem | G14: 2896.62 | H14: 8 | N14: 428.38 | S14: 0 | T14: =SUM(I14:S14) -> 428.38 | U14: =(T14-N14)*19.44% -> 0 | V14: 0 | W14: 0 | X14: =(T14+U14-N14)*41.8%-(L14) -> 0 | Y14: =SUM(T14:X14) -> 428.38
B15: Eliane Da Costa Santos | C15: 010.676.081-50 | D15: Tecnico De Enfermagem | G15: 2896.62 | H15: 8 | N15: 428.38 | S15: 0 | T15: =SUM(I15:S15) -> 428.38 | U15: =(T15-N15)*19.44% -> 0 | V15: 0 | W15: 0 | X15: =(T15+U15-N15)*41.8%-(L15) -> 0 | Y15: =SUM(T15:X15) -> 428.38
B16: Gisele Aparecida Soares Santana | C16: 014.785.481-42 | D16: Tecnico De Enfermagem | G16: 2896.62 | H16: 8 | N16: 428.38 | S16: 0 | T16: =SUM(I16:S16) -> 428.38 | U16: =(T16-N16)*19.44% -> 0 | V16: 0 | W16: 0 | X16: =(T16+U16-N16)*41.8%-(L16) -> 0 | Y16: =SUM(T16:X16) -> 428.38
B17: Kelly Kariny Gandes Silva | C17: 057.078.871-48 | D17: Tecnico De Enfermagem | G17: 2896.62 | H17: 8 | N17: 428.38 | S17: 0 | T17: =SUM(I17:S17) -> 428.38 | U17: =(T17-N17)*19.44% -> 0 | V17: 0 | W17: 0 | X17: =(T17+U17-N17)*41.8%-(L17) -> 0 | Y17: =SUM(T17:X17) -> 428.38
B18: Mariany Rosa Pereira | C18: 045.438.061-58 | D18: Tecnico De Enfermagem | G18: 2896.62 | H18: 8 | N18: 428.38 | S18: 0 | T18: =SUM(I18:S18) -> 428.38 | U18: =(T18-N18)*19.44% -> 0 | V18: 0 | W18: 0 | X18: =(T18+U18-N18)*41.8%-(L18) -> 0 | Y18: =SUM(T18:X18) -> 428.38
B19: Marilza Santana Silva Garcia | C19: 044.490.521-96 | D19: Tecnico De Enfermagem | G19: 2896.62 | H19: 8 | N19: 428.38 | S19: 0 | T19: =SUM(I19:S19) -> 428.38 | U19: =(T19-N19)*19.44% -> 0 | V19: 0 | W19: 0 | X19: =(T19+U19-N19)*41.8%-(L19) -> 0 | Y19: =SUM(T19:X19) -> 428.38
B20: Marina De Jesus Barreto Souza | C20: 010.618.831-32 | D20: Tecnico De Enfermagem | G20: 2896.62 | H20: 8 | N20: 428.38 | S20: 0 | T20: =SUM(I20:S20) -> 428.38 | U20: =(T20-N20)*19.44% -> 0 | V20: 0 | W20: 0 | X20: =(T20+U20-N20)*41.8%-(L20) -> 0 | Y20: =SUM(T20:X20) -> 428.38
B21: Najara Barbosa De Oliveira | C21: 039.013.111-30 | D21: Tecnico De Enfermagem | G21: 2896.62 | H21: 8 | N21: 428.38 | S21: 0 | T21: =SUM(I21:S21) -> 428.38 | U21: =(T21-N21)*19.44% -> 0 | V21: 0 | W21: 0 | X21: =(T21+U21-N21)*41.8%-(L21) -> 0 | Y21: =SUM(T21:X21) -> 428.38
B22: Vanessa Fernanda Garcia Barbosa | C22: 056.873.071-25 | D22: Tecnico De Enfermagem | G22: 2896.62 | H22: 8 | N22: 428.38 | S22: 0 | T22: =SUM(I22:S22) -> 428.38 | U22: =(T22-N22)*19.44% -> 0 | V22: 0 | W22: 0 | X22: =(T22+U22-N22)*41.8%-(L22) -> 0 | Y22: =SUM(T22:X22) -> 428.38
S23: 0 | T23: =SUM(I23:S23) -> 0 | U23: =(T23-N23)*19.44% -> 0 | V23: 0 | W23: 0 | X23: =(T23+U23)*41.8%-(L23) -> 0 | Y23: =SUM(V23:X23) -> 0
S24: 0 | T24: =SUM(I24:S24) -> 0 | U24: =(T24-N24)*19.44% -> 0 | V24: 0 | W24: 0 | X24: =(T24+U24)*41.8%-(L24) -> 0 | Y24: =SUM(V24:X24) -> 0
S25: 0 | T25: =SUM(I25:S25) -> 0 | U25: =(T25-N25)*19.44% -> 0 | V25: 0 | W25: 0 | X25: =(T25+U25)*41.8%-(L25) -> 0 | Y25: =SUM(V25:X25) -> 0
S26: 0 | T26: =SUM(I26:S26) -> 0 | U26: =(T26-N26)*19.44% -> 0 | V26: 0 | W26: 0 | X26: =(T26+U26)*41.8%-(L26) -> 0 | Y26: =SUM(V26:X26) -> 0
S27: 0 | T27: =SUM(I27:S27) -> 0 | U27: =(T27-N27)*19.44% -> 0 | V27: 0 | W27: 0 | X27: =(T27+U27)*41.8%-(L27) -> 0 | Y27: =SUM(V27:X27) -> 0
S28: 0 | T28: =SUM(I28:S28) -> 0 | U28: =(T28-N28)*19.44% -> 0 | V28: 0 | W28: 0 | X28: =(T28+U28)*41.8%-(L28) -> 0 | Y28: =SUM(V28:X28) -> 0
S29: 0 | T29: =SUM(I29:S29) -> 0 | U29: =(T29-N29)*19.44% -> 0 | V29: 0 | W29: 0 | X29: =(T29+U29)*41.8%-(L29) -> 0 | Y29: =SUM(V29:X29) -> 0
S30: 0 | T30: =SUM(I30:S30) -> 0 | U30: =(T30-N30)*19.44% -> 0 | V30: 0 | W30: 0 | X30: =(T30+U30)*41.8%-(L30) -> 0 | Y30: =SUM(V30:X30) -> 0
S31: 0 | T31: =SUM(I31:S31) -> 0 | U31: =(T31-N31)*19.44% -> 0 | V31: 0 | W31: 0 | X31: =(T31+U31)*41.8%-(L31) -> 0 | Y31: =SUM(V31:X31) -> 0
S32: 0 | T32: =SUM(I32:S32) -> 0 | U32: =(T32-N32)*19.44% -> 0 | V32: 0 | W32: 0 | X32: =(T32+U32)*41.8%-(L32) -> 0 | Y32: =SUM(V32:X32) -> 0
S33: 0 | T33: =SUM(I33:S33) -> 0 | U33: =(T33-N33)*19.44% -> 0 | V33: 0 | W33: 0 | X33: =(T33+U33)*41.8%-(L33) -> 0 | Y33: =SUM(V33:X33) -> 0
S34: 0 | T34: =SUM(I34:S34) -> 0 | U34: =(T34-N34)*19.44% -> 0 | V34: 0 | W34: 0 | X34: =(T34+U34)*41.8%-(L34) -> 0 | Y34: =SUM(V34:X34) -> 0
... S48: 0 | T48: =SUM(I48:S48) -> 0 | U48: =(T48-N48)*19.44% -> 0 | V48: 0 | W48: 0 | X48: =(T48+U48)*41.8%-(L48) -> 0 | Y48: =SUM(V48:X48) -> 0
A49: 391 | S49: 0
A50: 391 | S50: 0
B51: TOTAL | D51: =SUBTOTAL(3,D14:D48) -> 9 | E51: * | F51: * | G51: =SUBTOTAL(9,G14:G48) -> 26069.58 | I51: =SUBTOTAL(9,I14:I48) -> 0 | J51: =SUBTOTAL(9,J14:J48) -> 0 | K51: =SUBTOTAL(9,K14:K48) -> 0 | L51: =SUBTOTAL(9,L14:L48) -> 0 | M51: =SUBTOTAL(9,M14:M48) -> 0 | N51: =SUBTOTAL(9,N14:N48) -> 3855.42 | O51: =SUBTOTAL(9,O14:O48) -> 0 | P51: =SUBTOTAL(9,P14:P48) -> 0 | ... Y51: =SUBTOTAL(9,Y14:Y48) -> 3855.42

Sheet DETALHAMENTO PF
A2: ='RESUMO FATURAMENTO'!C1 -> PREFEITURA MUNICIPAL DE DOM AQUINO/MT
A3: ='RESUMO FATURAMENTO'!C3 -> TERMO DE PARCERIA Nº 001/2026
A4: ='RESUMO FATURAMENTO'!C4 -> SECRETARIA MUNICIPAL DE SAÚDE
A6: ='RESUMO FATURAMENTO'!A20 -> 1.1 - CLT
B8: ='RESUMO FATURAMENTO'!A9 -> OSCIP. ORGANIZAÇÃO DE SAÚDE SÃO BENTO | F8: ='DETALHAMENTO CLT'!G8 -> ÓRGÃO PARCEIRO: PREFEITURA MUNICIPAL DE DOM AQUINO/MT
B10: ='DETALHAMENTO CLT'!A10 -> SECRETARIA MUNICIPAL DE SAÚDE | F10: ='RESUMO FATURAMENTO'!A11 -> PROJETO FORSAÚDE – Fortalecimento da Saúde Pública Municipal
A12: ='RESUMO FATURAMENTO'!A15 -> COMPETÊNCIA. 01 A 31 DE AGOSTO DE 2026
A13: DESCRIÇÃO COLABORADOR/FUNÇÃO/SEÇÃO | H13: A | I13: B | J13: C | K13: D | L13: E | M13: F | N13: G | O13: H | P13: I | Q13: J | R13: K | S13: L | T13: M | U13: N
T15: (J-D-E-G)*37,80%(E) | U15: (J+K+L+M)
A16: Codigo Consisa | B16: Colaborador | C16: Função | D16: Função tabela | E16: Seção | F16: Situação | G16: Remuneração Base | H16: Remuneração | I16: Insalubridade | J16: Periculosidade | K16: Complemento Piso Enfermagem | L16: Salário Família | M16: Adicional Noturno | N16: Ajuda de Custo | O16: Faltas | P16: Provisão 19,44% | Q16: Sub Total | R16: Verbas Rescisórias | S16: Multa 40% | T16: Encargos Tributários 37,80% | U16: Valor Total
F17: Ativo | I17: 0 | K17: 0 | L17: 0 | M17: 0 | O17: 0 | P17: 0 | Q17: =SUM(H17:N17,P17)-O17 -> 0 | R17: 0 | S17: 0 | T17: 0 | U17: =SUM(Q17:T17) -> 0
F18: Ativo | I18: 0 | K18: 0 | L18: 0 | M18: 0 | O18: 0 | P18: 0 | Q18: =SUM(H18:N18,P18)-O18 -> 0 | R18: 0 | S18: 0 | T18: 0 | U18: =SUM(Q18:T18) -> 0
C19: =SUBTOTAL(3,C17:C18) -> 0 | D19: * | E19: * | F19: * | G19: =SUBTOTAL(9,G17:G18) -> 0 | H19: =SUBTOTAL(9,H17:H18) -> 0 | I19: =SUBTOTAL(9,I18:I18) -> 0 | J19: =SUBTOTAL(9,J18:J18) -> 0 | K19: =SUBTOTAL(9,K18:K18) -> 0 | L19: =SUBTOTAL(9,L18:L18) -> 0 | M19: =SUBTOTAL(9,M18:M18) -> 0 | N19: =SUBTOTAL(9,N18:N18) -> 0 | O19: =SUBTOTAL(9,O18:O18) -> 0 | P19: =SUBTOTAL(9,P18:P18) -> 0 | ... T19: =SUBTOTAL(9,T18:T18) -> 0 | U19: =SUBTOTAL(9,U17:U18) -> 0

Sheet DETALHAMENTO PJ SAUDE
A2: ='RESUMO FATURAMENTO'!C1 -> PREFEITURA MUNICIPAL DE DOM AQUINO/MT
A3: ='RESUMO FATURAMENTO'!C3 -> TERMO DE PARCERIA Nº 001/2026
A4: ='RESUMO FATURAMENTO'!C4 -> SECRETARIA MUNICIPAL DE SAÚDE
A5: ='RESUMO FATURAMENTO'!C5 -> TERMO DE PARCERIA Nº 001/2026
A7: ='RESUMO FATURAMENTO'!A21 -> 1.2 - PJ
A9: ='RESUMO FATURAMENTO'!A9 -> OSCIP. ORGANIZAÇÃO DE SAÚDE SÃO BENTO | E9: ='DETALHAMENTO CLT'!G8 -> ÓRGÃO PARCEIRO: PREFEITURA MUNICIPAL DE DOM AQUINO/MT
A11: ='RESUMO FATURAMENTO'!C4 -> SECRETARIA MUNICIPAL DE SAÚDE | E11: ='RESUMO FATURAMENTO'!A11 -> PROJETO FORSAÚDE – Fortalecimento da Saúde Pública Municipal
A13: ='RESUMO FATURAMENTO'!A15 -> COMPETÊNCIA. 01 A 31 DE AGOSTO DE 2026
A14: ITEM | B14: EMPRESA | C14: CNPJ | D14: PROFISSIONAL | E14: DOTAÇÃO | F14: ATIVIDADE | G14: TIPO | H14: LOCAL | I14: DATA INÍCIO | J14: REMUNERAÇÃO BASE | K14: REF | L14: VALOR
B15: 26.781.853 Marcela Luzia Araujo Da Silveira | C15: 26.781.853/0001-00 | D15: Marcela Luzia Araujo Da Silveira | E15: Secretaria de Saúde - MAC | F15: Motorista II | G15: =IFERROR(VLOOKUP(F15,'Referencia PT'!D:F,2,FALSE),"-") -> Serviço Mensal | I15: Serviços De Coordenação De Processos II | J15: =IFERROR(VLOOKUP(F15,'Referencia PT'!D:F,3,FALSE),"0") -> 2600 | K15: 31 | L15: =IF(G15="SERVIÇO MENSAL",((J15/31)*K15),(J15*K15)) -> 2600
B16: 26.781.853 Marcela Luzia Araujo Da Silveira | C16: 26.781.853/0001-00 | D16: Marcela Luzia Araujo Da Silveira | E16: Secretaria de Saúde - MAC | F16: Motorista - Plantão | G16: =IFERROR(VLOOKUP(F16,'Referencia PT'!D:F,2,FALSE),"-") -> Demanda | I16: Serviços De Coordenação De Processos II | J16: =IFERROR(VLOOKUP(F16,'Referencia PT'!D:F,3,FALSE),"0") -> 87 | K16: 1 | L16: =IF(G16="SERVIÇO MENSAL",((J16/31)*K16),(J16*K16)) -> 87
B17: 37.348.812 Aylla Angelica Monte Mendes | C17: 37.348.812/0001-32 | D17: Aylla Angelica Monte Mendes | E17: Secretaria de Saúde - APS/PAB | F17: Recepcionista II | G17: =IFERROR(VLOOKUP(F17,'Referencia PT'!D:F,2,FALSE),"-") -> Serviço Mensal | J17: =IFERROR(VLOOKUP(F17,'Referencia PT'!D:F,3,FALSE),"0") -> 1800 | K17: 31 | L17: =IF(G17="SERVIÇO MENSAL",((J17/31)*K17),(J17*K17)) -> 1800
B18: 51.090.950 Dejairson Joao Araujo Da Costa | C18: 51.090.950/0001-95 | D18: Dejairson Joao Araujo Da Costa | E18: Secretaria de Saúde - MAC | F18: Controlador de Frota | G18: =IFERROR(VLOOKUP(F18,'Referencia PT'!D:F,2,FALSE),"-") -> Serviço Mensal | J18: =IFERROR(VLOOKUP(F18,'Referencia PT'!D:F,3,FALSE),"0") -> 4000 | K18: 31 | L18: =IF(G18="SERVIÇO MENSAL",((J18/31)*K18),(J18*K18)) -> 4000
B19: 51.090.950 Dejairson Joao Araujo Da Costa | C19: 51.090.950/0001-95 | D19: Dejairson Joao Araujo Da Costa | E19: Secretaria de Saúde - MAC | F19: Controlador de Frota - Plantão | G19: =IFERROR(VLOOKUP(F19,'Referencia PT'!D:F,2,FALSE),"-") -> Demanda | J19: =IFERROR(VLOOKUP(F19,'Referencia PT'!D:F,3,FALSE),"0") -> 129.03226 | K19: 7.75 | L19: =IF(G19="SERVIÇO MENSAL",((J19/31)*K19),(J19*K19)) -> 1000
A20: 2 | B20: 51.304.838 Michela Cristina De Oliveira | C20: 51.304.838/0001-00 | D20: Michela Cristina De Oliveira | E20: Secretaria de Saúde - APS/PAB | F20: Recepcionista II | G20: =IFERROR(VLOOKUP(F20,'Referencia PT'!D:F,2,FALSE),"-") -> Serviço Mensal | J20: =IFERROR(VLOOKUP(F20,'Referencia PT'!D:F,3,FALSE),"0") -> 1800 | K20: 31 | L20: =IF(G20="SERVIÇO MENSAL",((J20/31)*K20),(J20*K20)) -> 1800
A21: 2 | B21: 51.509.678 Larissa da Silva Pessoa | C21: 51.509.678/0001-35 | D21: Larissa da Silva Pessoa | E21: Secretaria de Saúde - APS/PAB | F21: Educador Físico I | G21: =IFERROR(VLOOKUP(F21,'Referencia PT'!D:F,2,FALSE),"-") -> Serviço Mensal | J21: =IFERROR(VLOOKUP(F21,'Referencia PT'!D:F,3,FALSE),"0") -> 3300 | K21: 31 | L21: =IF(G21="SERVIÇO MENSAL",((J21/31)*K21),(J21*K21)) -> 3300
A22: 6 | B22: 51.961.971 Natalia Das Virgens Pacheco | C22: 51.961.971/0001-39 | D22: Natalia Das Virgens Pacheco | E22: Secretaria de Saúde - APS/PAB | F22: Motorista I | G22: =IFERROR(VLOOKUP(F22,'Referencia PT'!D:F,2,FALSE),"-") -> Serviço Mensal | J22: =IFERROR(VLOOKUP(F22,'Referencia PT'!D:F,3,FALSE),"0") -> 2400 | K22: 31 | L22: =IF(G22="SERVIÇO MENSAL",((J22/31)*K22),(J22*K22)) -> 2400
A23: 6 | B23: 51.961.971 Natalia Das Virgens Pacheco | C23: 51.961.971/0001-39 | D23: Natalia Das Virgens Pacheco | E23: Secretaria de Saúde - APS/PAB | F23: Motorista - Plantão | G23: =IFERROR(VLOOKUP(F23,'Referencia PT'!D:F,2,FALSE),"-") -> Demanda | J23: =IFERROR(VLOOKUP(F23,'Referencia PT'!D:F,3,FALSE),"0") -> 87 | K23: 3 | L23: =IF(G23="SERVIÇO MENSAL",((J23/31)*K23),(J23*K23)) -> 261
A24: 6 | B24: 53.834.087 Virlei Miranda De Souza | C24: 53.834.087/0001-69 | D24: Virlei Miranda De Souza | E24: Secretaria de Saúde - APS/PAB | F24: Motorista I | G24: =IFERROR(VLOOKUP(F24,'Referencia PT'!D:F,2,FALSE),"-") -> Serviço Mensal | J24: =IFERROR(VLOOKUP(F24,'Referencia PT'!D:F,3,FALSE),"0") -> 2400 | K24: 31 | L24: =IF(G24="SERVIÇO MENSAL",((J24/31)*K24),(J24*K24)) -> 2400
A25: 6 | B25: 53.870.742 Maria Aparecida Vilto Da Silva | C25: 53.870.742/0001-34 | D25: Maria Aparecida Vilto Da Silva | E25: Secretaria de Saúde - MAC | F25: Acompanhamento de Paciente | G25: =IFERROR(VLOOKUP(F25,'Referencia PT'!D:F,2,FALSE),"-") -> Serviço Mensal | J25: =IFERROR(VLOOKUP(F25,'Referencia PT'!D:F,3,FALSE),"0") -> 2500 | K25: 31 | L25: =IF(G25="SERVIÇO MENSAL",((J25/31)*K25),(J25*K25)) -> 2500
A26: 8 | B26: 53.981.677 Rafaela Soares Inacio | C26: 53.981.677/0001-14 | D26: Rafaela Soares Inacio | E26: Secretaria de Saúde - APS/PAB | F26: Agente de Conservação e Limpeza II | G26: =IFERROR(VLOOKUP(F26,'Referencia PT'!D:F,2,FALSE),"-") -> Serviço Mensal | J26: =IFERROR(VLOOKUP(F26,'Referencia PT'!D:F,3,FALSE),"0") -> 1800 | K26: 31 | L26: =IF(G26="SERVIÇO MENSAL",((J26/31)*K26),(J26*K26)) -> 1800
A27: 8 | B27: 54.114.115 Rosemeire Souza Ribeiro | C27: 54.114.115/0001-36 | D27: Rosemeire Souza Ribeiro | E27: Secretaria de Saúde - APS/PAB | F27: Agente de Conservação e Limpeza II | G27: =IFERROR(VLOOKUP(F27,'Referencia PT'!D:F,2,FALSE),"-") -> Serviço Mensal | J27: =IFERROR(VLOOKUP(F27,'Referencia PT'!D:F,3,FALSE),"0") -> 1800 | K27: 31 | L27: =IF(G27="SERVIÇO MENSAL",((J27/31)*K27),(J27*K27)) -> 1800
A28: 8 | B28: 54.632.340 Raul Torres Marques | C28: 54.632.340/0001-64 | D28: Raul Torres Marques | E28: Secretaria de Saúde - APS/PAB | F28: Motorista I | G28: =IFERROR(VLOOKUP(F28,'Referencia PT'!D:F,2,FALSE),"-") -> Serviço Mensal | J28: =IFERROR(VLOOKUP(F28,'Referencia PT'!D:F,3,FALSE),"0") -> 2400 | K28: 31 | L28: =IF(G28="SERVIÇO MENSAL",((J28/31)*K28),(J28*K28)) -> 2400
A29: 8 | B29: 54.632.340 Raul Torres Marques | C29: 54.632.340/0001-64 | D29: Raul Torres Marques | E29: Secretaria de Saúde - APS/PAB | F29: Motorista - Plantão | G29: =IFERROR(VLOOKUP(F29,'Referencia PT'!D:F,2,FALSE),"-") -> Demanda | J29: =IFERROR(VLOOKUP(F29,'Referencia PT'!D:F,3,FALSE),"0") -> 87 | K29: 2 | L29: =IF(G29="SERVIÇO MENSAL",((J29/31)*K29),(J29*K29)) -> 174
B30: 59.215.311 Bruna Taina Santin | C30: 59.215.311/0001-10 | D30: Bruna Taina Santin | E30: Secretaria de Saúde - APS/PAB | F30: Auxiliar de Saúde Bucal | G30: =IFERROR(VLOOKUP(F30,'Referencia PT'!D:F,2,FALSE),"-") -> Serviço Mensal | J30: =IFERROR(VLOOKUP(F30,'Referencia PT'!D:F,3,FALSE),"0") -> 2400 | K30: 31 | L30: =IF(G30="SERVIÇO MENSAL",((J30/31)*K30),(J30*K30)) -> 2400
B31: 59.373.454 Alecsandra Bezerra De Farias Bastos | C31: 59.373.454/0001-50 | D31: Alecsandra Bezerra De Farias Bastos | E31: Secretaria de Saúde - APS/PAB | F31: Agente de Conservação e Limpeza II | G31: =IFERROR(VLOOKUP(F31,'Referencia PT'!D:F,2,FALSE),"-") -> Serviço Mensal | J31: =IFERROR(VLOOKUP(F31,'Referencia PT'!D:F,3,FALSE),"0") -> 1800 | K31: =(31-12)+1 -> 20 | L31: =IF(G31="SERVIÇO MENSAL",((J31/31)*K31),(J31*K31)) -> 1161.2903
A32: 8 | B32: 59.688.729 Hamanda Aparecida De Oliveira Freitas | C32: 59.688.729/0001-45 | D32: Hamanda Aparecida De Oliveira Freitas | E32: Secretaria de Saúde - APS/PAB | F32: Técnico Administrativo II | G32: =IFERROR(VLOOKUP(F32,'Referencia PT'!D:F,2,FALSE),"-") -> Serviço Mensal | J32: =IFERROR(VLOOKUP(F32,'Referencia PT'!D:F,3,FALSE),"0") -> 2534.82 | K32: 31 | L32: =IF(G32="SERVIÇO MENSAL",((J32/31)*K32),(J32*K32)) -> 2534.82
B33: 59.688.729 Hamanda Aparecida De Oliveira Freitas | C33: 59.688.729/0001-45 | D33: Hamanda Aparecida De Oliveira Freitas | E33: Secretaria de Saúde - APS/PAB | F33: Técnico Administrativo II - Plantão | G33: =IFERROR(VLOOKUP(F33,'Referencia PT'!D:F,2,FALSE),"-") -> Demanda | J33: =IFERROR(VLOOKUP(F33,'Referencia PT'!D:F,3,FALSE),"0") -> 87 | K33: 6.2528736 | L33: =IF(G33="SERVIÇO MENSAL",((J33/31)*K33),(J33*K33)) -> 544
A34: 9 | B34: 59.711.381 Thome Da Silva Guedes Neto | C34: 59.711.381/0001-60 | D34: Thome Da Silva Guedes Neto | E34: Secretaria de Saúde - APS/PAB | F34: Motorista I | G34: =IFERROR(VLOOKUP(F34,'Referencia PT'!D:F,2,FALSE),"-") -> Serviço Mensal | J34: =IFERROR(VLOOKUP(F34,'Referencia PT'!D:F,3,FALSE),"0") -> 2400 | K34: 31 | L34: =IF(G34="SERVIÇO MENSAL",((J34/31)*K34),(J34*K34)) -> 2400
B35: 60.813.088 Felipe Jose Siqueira Santana Do Monte | C35: 60.813.088/0001-92 | D35: Felipe Jose Siqueira Santana Do Monte | E35: Secretaria de Saúde - MAC | F35: Motorista II | G35: =IFERROR(VLOOKUP(F35,'Referencia PT'!D:F,2,FALSE),"-") -> Serviço Mensal | J35: =IFERROR(VLOOKUP(F35,'Referencia PT'!D:F,3,FALSE),"0") -> 2600 | K35: 31 | L35: =IF(G35="SERVIÇO MENSAL",((J35/31)*K35),(J35*K35)) -> 2600
B36: 61.466.773 Arle Ferreira Leocardio | C36: 61.466.773/0001-52 | D36: Arle Ferreira Leocardio | E36: Secretaria de Saúde - APS/PAB | F36: Motorista II | G36: =IFERROR(VLOOKUP(F36,'Referencia PT'!D:F,2,FALSE),"-") -> Serviço Mensal | J36: =IFERROR(VLOOKUP(F36,'Referencia PT'!D:F,3,FALSE),"0") -> 2600 | K36: 31 | L36: =IF(G36="SERVIÇO MENSAL",((J36/31)*K36),(J36*K36)) -> 2600
B37: 61.466.773 Arle Ferreira Leocardio | C37: 61.466.773/0001-52 | D37: Arle Ferreira Leocardio | E37: Secretaria de Saúde - APS/PAB | F37: Motorista - Plantão | G37: =IFERROR(VLOOKUP(F37,'Referencia PT'!D:F,2,FALSE),"-") -> Demanda | J37: =IFERROR(VLOOKUP(F37,'Referencia PT'!D:F,3,FALSE),"0") -> 87 | K37: 2 | L37: =IF(G37="SERVIÇO MENSAL",((J37/31)*K37),(J37*K37)) -> 174
A38: 23 | B38: 62.157.459 Fabricio Nunes Camargo | C38: 62.157.459/0001-50 | D38: Fabricio Nunes Camargo | E38: Secretaria de Saúde - MAC | F38: Motorista II | G38: =IFERROR(VLOOKUP(F38,'Referencia PT'!D:F,2,FALSE),"-") -> Serviço Mensal | J38: =IFERROR(VLOOKUP(F38,'Referencia PT'!D:F,3,FALSE),"0") -> 2600 | K38: 31 | L38: =IF(G38="SERVIÇO MENSAL",((J38/31)*K38),(J38*K38)) -> 2600
B39: 62.185.423 Lidia Mikaelly Sousa Rodrigues | C39: 62.185.423/0001-80 | D39: Lidia Mikaelly Sousa Rodrigues | E39: Secretaria de Saúde - MAC | F39: Recepcionista IV | G39: =IFERROR(VLOOKUP(F39,'Referencia PT'!D:F,2,FALSE),"-") -> Serviço Mensal | J39: =IFERROR(VLOOKUP(F39,'Referencia PT'!D:F,3,FALSE),"0") -> 2200 | K39: 31 | L39: =IF(G39="SERVIÇO MENSAL",((J39/31)*K39),(J39*K39)) -> 2200
B40: 62.185.423 Lidia Mikaelly Sousa Rodrigues | C40: 62.185.423/0001-80 | D40: Lidia Mikaelly Sousa Rodrigues | E40: Secretaria de Saúde - MAC | F40: Recepcionista - Plantão | G40: =IFERROR(VLOOKUP(F40,'Referencia PT'!D:F,2,FALSE),"-") -> Demanda | J40: =IFERROR(VLOOKUP(F40,'Referencia PT'!D:F,3,FALSE),"0") -> 67 | K40: 2 | L40: =IF(G40="SERVIÇO MENSAL",((J40/31)*K40),(J40*K40)) -> 134
B41: 62.955.056 Rosa Ferreira | C41: 62.955.056/0001-57 | D41: Rosa Ferreira | E41: Secretaria de Saúde - MAC | F41: Técnico Administrativo II | G41: =IFERROR(VLOOKUP(F41,'Referencia PT'!D:F,2,FALSE),"-") -> Serviço Mensal | H41: PLANTONISTA | I41: 45293 | J41: =IFERROR(VLOOKUP(F41,'Referencia PT'!D:F,3,FALSE),"0") -> 2534.82 | K41: 31 | L41: =IF(G41="SERVIÇO MENSAL",((J41/31)*K41),(J41*K41)) -> 2534.82
A42: 15 | B42: 62.955.056 Rosa Ferreira | C42: 62.955.056/0001-57 | D42: Rosa Ferreira | E42: Secretaria de Saúde - MAC | F42: Técnico Administrativo II - Plantão | G42: =IFERROR(VLOOKUP(F42,'Referencia PT'!D:F,2,FALSE),"-") -> Demanda | H42: PLANTONISTA | I42: 45293 | J42: =IFERROR(VLOOKUP(F42,'Referencia PT'!D:F,3,FALSE),"0") -> 87 | K42: 5.7471264 | L42: =IF(G42="SERVIÇO MENSAL",((J42/31)*K42),(J42*K42)) -> 500
A43: 15 | B43: 62.955.671 Dayane De Jesus Souza Gomes | C43: 62.955.671/0001-63 | D43: Dayane De Jesus Souza Gomes | E43: Secretaria de Saúde - MAC | F43: Recepcionista III | G43: =IFERROR(VLOOKUP(F43,'Referencia PT'!D:F,2,FALSE),"-") -> Serviço Mensal | H43: PLANTONISTA | I43: 45293 | J43: =IFERROR(VLOOKUP(F43,'Referencia PT'!D:F,3,FALSE),"0") -> 2000 | K43: 31 | L43: =IF(G43="SERVIÇO MENSAL",((J43/31)*K43),(J43*K43)) -> 2000
A44: 15 | B44: 62.985.373 Nilzaete Bezerra De Farias | C44: 62.985.373/0001-16 | D44: Nilzaete Bezerra De Farias | E44: Secretaria de Saúde - MAC | F44: Serviços Gerais III | G44: =IFERROR(VLOOKUP(F44,'Referencia PT'!D:F,2,FALSE),"-") -> Serviço Mensal | J44: =IFERROR(VLOOKUP(F44,'Referencia PT'!D:F,3,FALSE),"0") -> 1800 | K44: =(31-12)+1 -> 20 | L44: =IF(G44="SERVIÇO MENSAL",((J44/31)*K44),(J44*K44)) -> 1161.2903
A45: 20 | B45: 63.023.268 Marilene Alves Conceicao | C45: 63.023.268/0001-69 | D45: Marilene Alves Conceicao | E45: Secretaria de Saúde - MAC | F45: Serviços Gerais III | G45: =IFERROR(VLOOKUP(F45,'Referencia PT'!D:F,2,FALSE),"-") -> Serviço Mensal | J45: =IFERROR(VLOOKUP(F45,'Referencia PT'!D:F,3,FALSE),"0") -> 1800 | K45: 31 | L45: =IF(G45="SERVIÇO MENSAL",((J45/31)*K45),(J45*K45)) -> 1800
B46: 63.178.258 Josiane Cristina Monte Moreira | C46: 63.178.258/0001-00 | D46: Josiane Cristina Monte Moreira | E46: Secretaria de Saúde - MAC | F46: Recepcionista III | G46: =IFERROR(VLOOKUP(F46,'Referencia PT'!D:F,2,FALSE),"-") -> Serviço Mensal | H46: PSF | I46: 45293 | J46: =IFERROR(VLOOKUP(F46,'Referencia PT'!D:F,3,FALSE),"0") -> 2000 | K46: 31 | L46: =IF(G46="SERVIÇO MENSAL",((J46/31)*K46),(J46*K46)) -> 2000
B47: 63.178.258 Josiane Cristina Monte Moreira | C47: 63.178.258/0001-00 | D47: Josiane Cristina Monte Moreira | E47: Secretaria de Saúde - MAC | F47: Recepcionista - Plantão | G47: =IFERROR(VLOOKUP(F47,'Referencia PT'!D:F,2,FALSE),"-") -> Demanda | H47: PSF | I47: 45293 | J47: =IFERROR(VLOOKUP(F47,'Referencia PT'!D:F,3,FALSE),"0") -> 67 | K47: 12 | L47: =IF(G47="SERVIÇO MENSAL",((J47/31)*K47),(J47*K47)) -> 804
A48: 24 | B48: 64.434.240 Aparecida Lucilene Lopes De Oliveira | C48: 64.434.240/0001-87 | D48: Aparecida Lucilene Lopes De Oliveira | E48: Secretaria de Saúde - MAC | F48: Serviços Gerais III | G48: =IFERROR(VLOOKUP(F48,'Referencia PT'!D:F,2,FALSE),"-") -> Serviço Mensal | H48: PSF | I48: 45293 | J48: =IFERROR(VLOOKUP(F48,'Referencia PT'!D:F,3,FALSE),"0") -> 1800 | K48: 31 | L48: =IF(G48="SERVIÇO MENSAL",((J48/31)*K48),(J48*K48)) -> 1800
A49: 24 | B49: 64.434.240 Aparecida Lucilene Lopes De Oliveira | C49: 64.434.240/0001-87 | D49: Aparecida Lucilene Lopes De Oliveira | E49: Secretaria de Saúde - MAC | F49: Serviços Gerais - Plantão | G49: =IFERROR(VLOOKUP(F49,'Referencia PT'!D:F,2,FALSE),"-") -> Demanda | H49: PSF | I49: 45293 | J49: =IFERROR(VLOOKUP(F49,'Referencia PT'!D:F,3,FALSE),"0") -> 60 | K49: 15 | L49: =IF(G49="SERVIÇO MENSAL",((J49/31)*K49),(J49*K49)) -> 900
A50: 24 | B50: 65.353.941 Matheus Henrique de Avelino Santos | C50: 65.353.941/0001-54 | D50: Matheus Henrique de Avelino Santos | E50: Secretaria de Saúde - APS/PAB | F50: Motorista II | G50: =IFERROR(VLOOKUP(F50,'Referencia PT'!D:F,2,FALSE),"-") -> Serviço Mensal | H50: PSF | I50: 45293 | J50: =IFERROR(VLOOKUP(F50,'Referencia PT'!D:F,3,FALSE),"0") -> 2600 | K50: 31 | L50: =IF(G50="SERVIÇO MENSAL",((J50/31)*K50),(J50*K50)) -> 2600
A51: 24 | B51: 65.353.941 Matheus Henrique de Avelino Santos | C51: 65.353.941/0001-54 | D51: Matheus Henrique de Avelino Santos | E51: Secretaria de Saúde - APS/PAB | F51: Motorista - Plantão | G51: =IFERROR(VLOOKUP(F51,'Referencia PT'!D:F,2,FALSE),"-") -> Demanda | H51: PSF | I51: 45293 | J51: =IFERROR(VLOOKUP(F51,'Referencia PT'!D:F,3,FALSE),"0") -> 87 | K51: 5 | L51: =IF(G51="SERVIÇO MENSAL",((J51/31)*K51),(J51*K51)) -> 435
A52: 25 | B52: 65.406.041 Naiara da Silva Rodrigues | C52: 65.406.041/0001-28 | D52: Naiara da Silva Rodrigues | E52: Secretaria de Saúde - MAC | F52: Serviços Gerais III | G52: =IFERROR(VLOOKUP(F52,'Referencia PT'!D:F,2,FALSE),"-") -> Serviço Mensal | H52: PSF | I52: 45293 | J52: =IFERROR(VLOOKUP(F52,'Referencia PT'!D:F,3,FALSE),"0") -> 1800 | K52: 31 | L52: =IF(G52="SERVIÇO MENSAL",((J52/31)*K52),(J52*K52)) -> 1800
A53: 25 | B53: 65.989.197 Kener Roger da Rocha Silva | C53: 65.989.197/0001-89 | D53: Kener Roger da Rocha Silva | E53: Secretaria de Saúde - APS/PAB | F53: Educador Físico I | G53: =IFERROR(VLOOKUP(F53,'Referencia PT'!D:F,2,FALSE),"-") -> Serviço Mensal | H53: PSF | I53: 45293 | J53: =IFERROR(VLOOKUP(F53,'Referencia PT'!D:F,3,FALSE),"0") -> 3300 | K53: 31 | L53: =IF(G53="SERVIÇO MENSAL",((J53/31)*K53),(J53*K53)) -> 3300
A54: 27 | B54: 66.028.321 Andressa Bruna Costa Laranjeira | C54: 66.028.321/0001-02 | D54: Andressa Bruna Costa Laranjeira | E54: Secretaria de Saúde - MAC | F54: Recepcionista IV | G54: =IFERROR(VLOOKUP(F54,'Referencia PT'!D:F,2,FALSE),"-") -> Serviço Mensal | H54: PSF | I54: 45293 | J54: =IFERROR(VLOOKUP(F54,'Referencia PT'!D:F,3,FALSE),"0") -> 2200 | K54: 31 | L54: =IF(G54="SERVIÇO MENSAL",((J54/31)*K54),(J54*K54)) -> 2200
B55: 66.181.724 Rosicleide Maria da Conceicao dos Santos | C55: 66.181.724/0001-97 | D55: Rosicleide Maria da Conceicao dos Santos | E55: Secretaria de Saúde - MAC | F55: Serviços Gerais III | G55: =IFERROR(VLOOKUP(F55,'Referencia PT'!D:F,2,FALSE),"-") -> Serviço Mensal | H55: PSF | I55: 45293 | J55: =IFERROR(VLOOKUP(F55,'Referencia PT'!D:F,3,FALSE),"0") -> 1800 | K55: 31 | L55: =IF(G55="SERVIÇO MENSAL",((J55/31)*K55),(J55*K55)) -> 1800
B56: 67.798.050 Irani Francisca da Silva | C56: 67.798.050/0001-37 | D56: Irani Francisca da Sillva | E56: Secretaria de Saúde - MAC | F56: Serviços Gerais III | G56: =IFERROR(VLOOKUP(F56,'Referencia PT'!D:F,2,FALSE),"-") -> Serviço Mensal | H56: PSF | I56: 45293 | J56: =IFERROR(VLOOKUP(F56,'Referencia PT'!D:F,3,FALSE),"0") -> 1800 | K56: 31 | L56: =IF(G56="SERVIÇO MENSAL",((J56/31)*K56),(J56*K56)) -> 1800
B57: 68.151.322 Maria Aparecida Gomes Silva | C57: 68.151.322/0001-75 | D57: Maria Aparecida Gomes Silva | E57: Secretaria de Saúde - MAC | F57: Agente de Conservação e Limpeza II | G57: =IFERROR(VLOOKUP(F57,'Referencia PT'!D:F,2,FALSE),"-") -> Serviço Mensal | H57: PSF | I57: 45293 | J57: =IFERROR(VLOOKUP(F57,'Referencia PT'!D:F,3,FALSE),"0") -> 1800 | K57: 31 | L57: =IF(G57="SERVIÇO MENSAL",((J57/31)*K57),(J57*K57)) -> 1800
B58: 68.442.629 Marcia Silva e Souza | C58: 68.442.629/0001-25 | D58: Marcia Silva e Souza | E58: Secretaria de Saúde - APS/PAB | F58: Recepcionista II | G58: =IFERROR(VLOOKUP(F58,'Referencia PT'!D:F,2,FALSE),"-") -> Serviço Mensal | H58: PSF | I58: 45293 | J58: =IFERROR(VLOOKUP(F58,'Referencia PT'!D:F,3,FALSE),"0") -> 1800 | K58: =(31-10)+1 -> 22 | L58: =IF(G58="SERVIÇO MENSAL",((J58/31)*K58),(J58*K58)) -> 1277.4194
A59: 28 | B59: A. Decesaro LTDA | C59: 54.015.720/0001-50 | D59: Arlindo Decesaro | E59: Secretaria de Saúde - MAC | F59: Médico Clínico – Plantão 12h | G59: =IFERROR(VLOOKUP(F59,'Referencia PT'!D:F,2,FALSE),"-") -> Demanda | H59: PSF | I59: 45293 | J59: =IFERROR(VLOOKUP(F59,'Referencia PT'!D:F,3,FALSE),"0") -> 1400 | K59: 12 | L59: =IF(G59="SERVIÇO MENSAL",((J59/31)*K59),(J59*K59)) -> 16800
B60: Adienni Leandro Dos Santos Ltda | C60: 60.002.682/0001-01 | D60: Adienni Leandro Dos Santos | E60: Secretaria de Saúde - APS/PAB | F60: Enfermeiro | G60: =IFERROR(VLOOKUP(F60,'Referencia PT'!D:F,2,FALSE),"-") -> Serviço Mensal | H60: PSF | I60: 45293 | J60: =IFERROR(VLOOKUP(F60,'Referencia PT'!D:F,3,FALSE),"0") -> 4770 | K60: 31 | L60: =IF(G60="SERVIÇO MENSAL",((J60/31)*K60),(J60*K60)) -> 4770
A61: 47 | B61: Adienni Leandro Dos Santos Ltda | C61: 60.002.682/0001-01 | D61: Adienni Leandro Dos Santos | E61: Secretaria de Saúde - APS/PAB | F61: Enfermeiro - Plantão | G61: =IFERROR(VLOOKUP(F61,'Referencia PT'!D:F,2,FALSE),"-") -> Demanda | H61: PSF | I61: 45293 | J61: =IFERROR(VLOOKUP(F61,'Referencia PT'!D:F,3,FALSE),"0") -> 159 | K61: 1 | L61: =IF(G61="SERVIÇO MENSAL",((J61/31)*K61),(J61*K61)) -> 159
A62: 47 | B62: Aline Lopes Moraes da Silva Ltda | C62: 65.533.131/0001-80 | D62: Aline Lopes Moraes da Silva | E62: Secretaria de Saúde - MAC | F62: Bioquímico I | G62: =IFERROR(VLOOKUP(F62,'Referencia PT'!D:F,2,FALSE),"-") -> Serviço Mensal | H62: PSF | I62: 45293 | J62: =IFERROR(VLOOKUP(F62,'Referencia PT'!D:F,3,FALSE),"0") -> 5112 | K62: 31 | L62: =IF(G62="SERVIÇO MENSAL",((J62/31)*K62),(J62*K62)) -> 5112
A63: 30 | B63: Atendimento Medico SB Med Ltda | C63: 44.399.312/0001-95 | D63: Luan Santos Bomucia | E63: Secretaria de Saúde - MAC | F63: Coordenador de Unidade de Saúde | G63: =IFERROR(VLOOKUP(F63,'Referencia PT'!D:F,2,FALSE),"-") -> Serviço Mensal | H63: PLANTONISTA | I63: 45293 | J63: =IFERROR(VLOOKUP(F63,'Referencia PT'!D:F,3,FALSE),"0") -> 6000 | K63: 31 | L63: =IF(G63="SERVIÇO MENSAL",((J63/31)*K63),(J63*K63)) -> 6000
A64: 1 | B64: Atendimento Medico SB Med Ltda | C64: 44.399.312/0001-95 | D64: Luan Santos Bomucia | E64: Secretaria de Saúde - MAC | F64: Médico Clínico – Plantão 12h | G64: =IFERROR(VLOOKUP(F64,'Referencia PT'!D:F,2,FALSE),"-") -> Demanda | H64: PLANTONISTA | I64: 45293 | J64: =IFERROR(VLOOKUP(F64,'Referencia PT'!D:F,3,FALSE),"0") -> 1400 | K64: 9 | L64: =IF(G64="SERVIÇO MENSAL",((J64/31)*K64),(J64*K64)) -> 12600
A65: 1 | B65: C S Odontologia Ltda | C65: 48.536.275/0001-70 | D65: Camila Soares dos Santos | E65: Secretaria de Saúde - APS/PAB | F65: Coordenador Administrativo | G65: =IFERROR(VLOOKUP(F65,'Referencia PT'!D:F,2,FALSE),"-") -> Serviço Mensal | H65: PLANTONISTA | I65: 45293 | J65: =IFERROR(VLOOKUP(F65,'Referencia PT'!D:F,3,FALSE),"0") -> 5200 | K65: 31 | L65: =IF(G65="SERVIÇO MENSAL",((J65/31)*K65),(J65*K65)) -> 5200
A66: 1 | B66: C S Odontologia Ltda | C66: 48.536.275/0001-70 | D66: Camila Soares dos Santos | E66: Secretaria de Saúde - APS/PAB | F66: Coordernador Administrativo - Plantão | G66: =IFERROR(VLOOKUP(F66,'Referencia PT'!D:F,2,FALSE),"-") -> Demanda | H66: PLANTONISTA | I66: 45293 | J66: =IFERROR(VLOOKUP(F66,'Referencia PT'!D:F,3,FALSE),"0") -> 190 | K66: 2 | L66: =IF(G66="SERVIÇO MENSAL",((J66/31)*K66),(J66*K66)) -> 380
A67: 1 | B67: Cecilia Moraes Da Silva Oliveira Ltda | C67: 63.209.179/0001-01 | D67: Cecilia Moraes Da Silva Oliveira | E67: Secretaria de Saúde - MAC | F67: Farmacêutico | G67: =IFERROR(VLOOKUP(F67,'Referencia PT'!D:F,2,FALSE),"-") -> Serviço Mensal | H67: PSF | I67: 45293 | J67: =IFERROR(VLOOKUP(F67,'Referencia PT'!D:F,3,FALSE),"0") -> 4770 | K67: 31 | L67: =IF(G67="SERVIÇO MENSAL",((J67/31)*K67),(J67*K67)) -> 4770
A68: 1 | B68: Clinica Mohr LTDA | C68: 55.596.304/0001-55 | D68: Suelen Cristina Mohr | E68: Secretaria de Saúde - APS/PAB | F68: Psicólogo II | G68: =IFERROR(VLOOKUP(F68,'Referencia PT'!D:F,2,FALSE),"-") -> Serviço Mensal | H68: PSF | I68: 45293 | J68: =IFERROR(VLOOKUP(F68,'Referencia PT'!D:F,3,FALSE),"0") -> 5066.16 | K68: 31 | L68: =IF(G68="SERVIÇO MENSAL",((J68/31)*K68),(J68*K68)) -> 5066.16
B69: Clinica Odontologica Ltda | C69: 48.631.083/0001-43 | D69: Danielly Gonçalves da Silva | E69: Secretaria de Saúde - APS/PAB | F69: Dentista | G69: =IFERROR(VLOOKUP(F69,'Referencia PT'!D:F,2,FALSE),"-") -> Serviço Mensal | H69: PSF | I69: 45293 | J69: =IFERROR(VLOOKUP(F69,'Referencia PT'!D:F,3,FALSE),"0") -> 4770 | K69: 31 | L69: =IF(G69="SERVIÇO MENSAL",((J69/31)*K69),(J69*K69)) -> 4770
A70: 38 | B70: Elaine C Laranjeira Ltda | C70: 68.426.593/0001-96 | D70: Elaine Costa Laranjeira | E70: Secretaria de Saúde - APS/PAB | F70: Assistente Social | G70: =IFERROR(VLOOKUP(F70,'Referencia PT'!D:F,2,FALSE),"-") -> Serviço Mensal | H70: PSF | I70: 45293 | J70: =IFERROR(VLOOKUP(F70,'Referencia PT'!D:F,3,FALSE),"0") -> 3300 | K70: =(31-7)+1 -> 25 | L70: =IF(G70="SERVIÇO MENSAL",((J70/31)*K70),(J70*K70)) -> 2661.2903
A71: 40 | B71: Emilly Oliveira Silva Cruz | C71: 44.413.776/0001-09 | D71: Emilly Oliveira Silva Cruz | E71: Secretaria de Saúde - APS/PAB | F71: Médico Clínico Geral | G71: =IFERROR(VLOOKUP(F71,'Referencia PT'!D:F,2,FALSE),"-") -> Serviço Mensal | H71: PSF | I71: 45293 | J71: =IFERROR(VLOOKUP(F71,'Referencia PT'!D:F,3,FALSE),"0") -> 19500 | K71: 31 | L71: =IF(G71="SERVIÇO MENSAL",((J71/31)*K71),(J71*K71)) -> 19500
A72: 40 | B72: Emilly Oliveira Silva Cruz | C72: 44.413.776/0001-09 | D72: Emilly Oliveira Silva Cruz | E72: Secretaria de Saúde - MAC | F72: Médico Clínico – Plantão 12h | G72: =IFERROR(VLOOKUP(F72,'Referencia PT'!D:F,2,FALSE),"-") -> Demanda | H72: PSF | I72: 45293 | J72: =IFERROR(VLOOKUP(F72,'Referencia PT'!D:F,3,FALSE),"0") -> 1400 | K72: 4 | L72: =IF(G72="SERVIÇO MENSAL",((J72/31)*K72),(J72*K72)) -> 5600
A73: 42 | B73: Érica Enfermagem | C73: 53.802.649/0001-92 | D73: Érica da Silva Pereira | E73: Secretaria de Saúde - APS/PAB | F73: Enfermeiro | G73: =IFERROR(VLOOKUP(F73,'Referencia PT'!D:F,2,FALSE),"-") -> Serviço Mensal | H73: PSF | I73: 45293 | J73: =IFERROR(VLOOKUP(F73,'Referencia PT'!D:F,3,FALSE),"0") -> 4770 | K73: 31 | L73: =IF(G73="SERVIÇO MENSAL",((J73/31)*K73),(J73*K73)) -> 4770
A74: 42 | B74: Erick Ricardo Reis Rodrigues | C74: 46.424.433/0001-75 | D74: Erick Ricardo Reis Rodrigues | E74: Secretaria de Saúde - APS/PAB | F74: Médico Clínico Geral | G74: =IFERROR(VLOOKUP(F74,'Referencia PT'!D:F,2,FALSE),"-") -> Serviço Mensal | H74: PSF | I74: 45293 | J74: =IFERROR(VLOOKUP(F74,'Referencia PT'!D:F,3,FALSE),"0") -> 19500 | K74: 31 | L74: =IF(G74="SERVIÇO MENSAL",((J74/31)*K74),(J74*K74)) -> 19500
A75: 42 | B75: Erick Ricardo Reis Rodrigues | C75: 46.424.433/0001-75 | D75: Erick Ricardo Reis Rodrigues | E75: Secretaria de Saúde - APS/PAB | F75: Médico Clínico Geral | G75: =IFERROR(VLOOKUP(F75,'Referencia PT'!D:F,2,FALSE),"-") -> Serviço Mensal | H75: PSF | I75: 45293 | J75: =IFERROR(VLOOKUP(F75,'Referencia PT'!D:F,3,FALSE),"0") -> 19500 | K75: 1 | L75: =IF(G75="SERVIÇO MENSAL",((J75/30)*K75),(J75*K75))+(19500*10%) -> 2600
A76: 42 | B76: Essencialmed Serviços Ltda | C76: 68.270.946/0001-01 | D76: Higor Souto Azambuja | E76: Secretaria de Saúde - MAC | F76: Médico Clínico – Plantão 12h | G76: =IFERROR(VLOOKUP(F76,'Referencia PT'!D:F,2,FALSE),"-") -> Demanda | H76: PSF | I76: 45293 | J76: =IFERROR(VLOOKUP(F76,'Referencia PT'!D:F,3,FALSE),"0") -> 1400 | K76: 5 | L76: =IF(G76="SERVIÇO MENSAL",((J76/31)*K76),(J76*K76)) -> 7000
A77: 42 | B77: Florescer Psicologia Ltda | C77: 60.074.313/0001-16 | D77: Joao Marcos Farias Maciel | E77: Secretaria de Saúde - MAC | F77: Psicólogo I | G77: =IFERROR(VLOOKUP(F77,'Referencia PT'!D:F,2,FALSE),"-") -> Serviço Mensal | H77: PSF | I77: 45293 | J77: =IFERROR(VLOOKUP(F77,'Referencia PT'!D:F,3,FALSE),"0") -> 3300 | K77: 31 | L77: =IF(G77="SERVIÇO MENSAL",((J77/31)*K77),(J77*K77)) -> 3300
A78: 24 | B78: Francielle De Carli Ltda | C78: 59.533.132/0001-21 | D78: Francielle De Carli | E78: Secretaria de Saúde - APS/PAB | F78: Farmacêutico | G78: =IFERROR(VLOOKUP(F78,'Referencia PT'!D:F,2,FALSE),"-") -> Serviço Mensal | H78: PSF | I78: 45293 | J78: =IFERROR(VLOOKUP(F78,'Referencia PT'!D:F,3,FALSE),"0") -> 4770 | K78: 31 | L78: =IF(G78="SERVIÇO MENSAL",((J78/31)*K78),(J78*K78)) -> 4770
A79: 24 | B79: GMR Assistencia em Enfermagem | C79: 65.450.071/0001-31 | D79: Gabriele Morais Rodrigues | E79: Secretaria de Saúde - MAC | F79: Enfermeiro Noturno | G79: =IFERROR(VLOOKUP(F79,'Referencia PT'!D:F,2,FALSE),"-") -> Serviço Mensal | H79: PSF | I79: 45293 | J79: =IFERROR(VLOOKUP(F79,'Referencia PT'!D:F,3,FALSE),"0") -> 5200 | K79: 31 | L79: =IF(G79="SERVIÇO MENSAL",((J79/31)*K79),(J79*K79)) -> 5200
A80: 24 | B80: Joao Arrais Serviços Medicos Ltda | C80: 54.059.010/0001-21 | D80: João Teotonio Arrais Neto | E80: Secretaria de Saúde - MAC | F80: Médico Clínico – Plantão 12h | G80: =IFERROR(VLOOKUP(F80,'Referencia PT'!D:F,2,FALSE),"-") -> Demanda | H80: PSF | I80: 45293 | J80: =IFERROR(VLOOKUP(F80,'Referencia PT'!D:F,3,FALSE),"0") -> 1400 | K80: 11 | L80: =IF(G80="SERVIÇO MENSAL",((J80/31)*K80),(J80*K80)) -> 15400
A81: 24 | B81: Jovelina S Muniz | C81: 54.021.630/0001-71 | D81: Jovelina Sateles Muniz | E81: Secretaria de Saúde - APS/PAB | F81: Enfermeiro | G81: =IFERROR(VLOOKUP(F81,'Referencia PT'!D:F,2,FALSE),"-") -> Serviço Mensal | H81: PSF | I81: 45293 | J81: =IFERROR(VLOOKUP(F81,'Referencia PT'!D:F,3,FALSE),"0") -> 4770 | K81: 31 | L81: =IF(G81="SERVIÇO MENSAL",((J81/31)*K81),(J81*K81)) -> 4770
A82: 24 | B82: Laiza Ramos Serviços Medicos LTDA | C82: 54.114.425/0001-50 | D82: Laiza Caroline Ramos Martelli | E82: Secretaria de Saúde - MAC | F82: Médico Clínico – Plantão 12h | G82: =IFERROR(VLOOKUP(F82,'Referencia PT'!D:F,2,FALSE),"-") -> Demanda | H82: PSF | I82: 45293 | J82: =IFERROR(VLOOKUP(F82,'Referencia PT'!D:F,3,FALSE),"0") -> 1400 | K82: 4 | L82: =IF(G82="SERVIÇO MENSAL",((J82/31)*K82),(J82*K82)) -> 5600
A83: 24 | B83: Leticia Deola Vieira Serviços Médicos LTDA | C83: 58.407.468/0001-85 | D83: Leticia Deola Vieira | E83: Secretaria de Saúde - MAC | F83: Médico Clínico – Plantão 12h | G83: =IFERROR(VLOOKUP(F83,'Referencia PT'!D:F,2,FALSE),"-") -> Demanda | H83: PSF | I83: 45293 | J83: =IFERROR(VLOOKUP(F83,'Referencia PT'!D:F,3,FALSE),"0") -> 1400 | K83: 5 | L83: =IF(G83="SERVIÇO MENSAL",((J83/31)*K83),(J83*K83)) -> 7000
A84: 25 | B84: Leticia Holsbaque Da Silva Ltda | C84: 39.531.078/0001-78 | D84: Leticia Holsbaque Da Silva | E84: Secretaria de Saúde - APS/PAB | F84: Médico Clínico Geral | G84: =IFERROR(VLOOKUP(F84,'Referencia PT'!D:F,2,FALSE),"-") -> Serviço Mensal | H84: PSF | I84: 45293 | J84: =IFERROR(VLOOKUP(F84,'Referencia PT'!D:F,3,FALSE),"0") -> 19500 | K84: 31 | L84: =IF(G84="SERVIÇO MENSAL",((J84/31)*K84),(J84*K84)) -> 19500
A85: 27 | B85: Leticia Holsbaque Da Silva Ltda | C85: 39.531.078/0001-78 | D85: Leticia Holsbaque Da Silva | E85: Secretaria de Saúde - MAC | F85: Médico Clínico – Plantão 12h | G85: =IFERROR(VLOOKUP(F85,'Referencia PT'!D:F,2,FALSE),"-") -> Demanda | H85: PSF | I85: 45293 | J85: =IFERROR(VLOOKUP(F85,'Referencia PT'!D:F,3,FALSE),"0") -> 1400 | K85: 12 | L85: =IF(G85="SERVIÇO MENSAL",((J85/31)*K85),(J85*K85)) -> 16800
B86: Maida Fernanda Pereira De Oliveira Ltda | C86: 61.522.062/0001-58 | D86: Maida Fernanda Pereira De Oliveira | E86: Secretaria de Saúde - APS/PAB | F86: Fisioterapeuta | G86: =IFERROR(VLOOKUP(F86,'Referencia PT'!D:F,2,FALSE),"-") -> Serviço Mensal | H86: PSF | I86: 45293 | J86: =IFERROR(VLOOKUP(F86,'Referencia PT'!D:F,3,FALSE),"0") -> 3862.16 | K86: 31 | L86: =IF(G86="SERVIÇO MENSAL",((J86/31)*K86),(J86*K86)) -> 3862.16
B87: Maos Que Cuidam Ltda | C87: 63.049.582/0001-10 | D87: Amanda De Oliveira Delfino | E87: Secretaria de Saúde - MAC | F87: Enfermeiro Diurno | G87: =IFERROR(VLOOKUP(F87,'Referencia PT'!D:F,2,FALSE),"-") -> Serviço Mensal | H87: PSF | I87: 45293 | J87: =IFERROR(VLOOKUP(F87,'Referencia PT'!D:F,3,FALSE),"0") -> 4950 | K87: 31 | L87: =IF(G87="SERVIÇO MENSAL",((J87/31)*K87),(J87*K87)) -> 4950
B88: MVRC - Servicos Odontologicos Ltda | C88: 48.770.674/0001-00 | D88: Marcello Vieira Rodrigues da Cruz | E88: Secretaria de Saúde - APS/PAB | F88: Dentista | G88: =IFERROR(VLOOKUP(F88,'Referencia PT'!D:F,2,FALSE),"-") -> Serviço Mensal | H88: PSF | I88: 45293 | J88: =IFERROR(VLOOKUP(F88,'Referencia PT'!D:F,3,FALSE),"0") -> 4770 | K88: 31 | L88: =IF(G88="SERVIÇO MENSAL",((J88/31)*K88),(J88*K88)) -> 4770
B89: Natale C Guedes da Silva | C89: 54.014.269/0001-56 | D89: Natale Christina Guedes da Silva | E89: Secretaria de Saúde - APS/PAB | F89: Enfermeiro | G89: =IFERROR(VLOOKUP(F89,'Referencia PT'!D:F,2,FALSE),"-") -> Serviço Mensal | H89: PSF | I89: 45293 | J89: =IFERROR(VLOOKUP(F89,'Referencia PT'!D:F,3,FALSE),"0") -> 4770 | K89: 31 | L89: =IF(G89="SERVIÇO MENSAL",((J89/31)*K89),(J89*K89)) -> 4770
B90: Oromi Ferreira De Sousa 14175576134 | C90: 43.933.385/0001-52 | D90: Oromi Ferreira De Sousa | E90: Secretaria de Saúde - MAC | F90: Motorista II | G90: =IFERROR(VLOOKUP(F90,'Referencia PT'!D:F,2,FALSE),"-") -> Serviço Mensal | H90: PLANTONISTA | I90: 45293 | J90: =IFERROR(VLOOKUP(F90,'Referencia PT'!D:F,3,FALSE),"0") -> 2600 | K90: 31 | L90: =IF(G90="SERVIÇO MENSAL",((J90/31)*K90),(J90*K90)) -> 2600
A91: 28 | B91: Oromi Ferreira De Sousa 14175576134 | C91: 43.933.385/0001-52 | D91: Oromi Ferreira De Sousa | E91: Secretaria de Saúde - MAC | F91: Motorista - Plantão | G91: =IFERROR(VLOOKUP(F91,'Referencia PT'!D:F,2,FALSE),"-") -> Demanda | H91: PLANTONISTA | I91: 45293 | J91: =IFERROR(VLOOKUP(F91,'Referencia PT'!D:F,3,FALSE),"0") -> 87 | K91: 4 | L91: =IF(G91="SERVIÇO MENSAL",((J91/31)*K91),(J91*K91)) -> 348
B92: P C P De Araujo Ltda | C92: 53.838.274/0001-10 | D92: Patricia Cristina Pereira De Araujo | E92: Secretaria de Saúde - APS/PAB | F92: Enfermeiro | G92: =IFERROR(VLOOKUP(F92,'Referencia PT'!D:F,2,FALSE),"-") -> Serviço Mensal | H92: PLANTONISTA | I92: 45293 | J92: =IFERROR(VLOOKUP(F92,'Referencia PT'!D:F,3,FALSE),"0") -> 4770 | K92: 31 | L92: =IF(G92="SERVIÇO MENSAL",((J92/31)*K92),(J92*K92)) -> 4770
A93: 47 | B93: Primecare Representacoes Ltda | C93: 63.031.503/0001-44 | D93: Dener Amaral Freitas | E93: Secretaria de Saúde - MAC | F93: Enfermeiro Noturno | G93: =IFERROR(VLOOKUP(F93,'Referencia PT'!D:F,2,FALSE),"-") -> Serviço Mensal | H93: PLANTONISTA | I93: 45293 | J93: =IFERROR(VLOOKUP(F93,'Referencia PT'!D:F,3,FALSE),"0") -> 5200 | K93: 31 | L93: =IF(G93="SERVIÇO MENSAL",((J93/31)*K93),(J93*K93)) -> 5200
A94: 30 | B94: Rafaela Pozzobon - Cirurgia Dentista Ltda | C94: 60.488.360/0001-06 | D94: Rafaela Ferreira Pozzobon Flores | E94: Secretaria de Saúde - APS/PAB | F94: Dentista | G94: =IFERROR(VLOOKUP(F94,'Referencia PT'!D:F,2,FALSE),"-") -> Serviço Mensal | H94: PSF | I94: 45293 | J94: =IFERROR(VLOOKUP(F94,'Referencia PT'!D:F,3,FALSE),"0") -> 4770 | K94: 31 | L94: =IF(G94="SERVIÇO MENSAL",((J94/31)*K94),(J94*K94)) -> 4770
A95: 1 | B95: Rafaella F de Oliveira Alves | C95: 55.549.443/0001-28 | D95: Rafaella Ferreira de Oliveira Alves | E95: Secretaria de Saúde - APS/PAB | F95: Fisioterapeuta | G95: =IFERROR(VLOOKUP(F95,'Referencia PT'!D:F,2,FALSE),"-") -> Serviço Mensal | H95: PSF | I95: 45293 | J95: =IFERROR(VLOOKUP(F95,'Referencia PT'!D:F,3,FALSE),"0") -> 3862.16 | K95: 31 | L95: =IF(G95="SERVIÇO MENSAL",((J95/31)*K95),(J95*K95)) -> 3862.16
A96: 1 | B96: Silvia ferreira Da Silva | C96: 63.068.051/0001-75 | D96: Silvia ferreira Da Silva | E96: Secretaria de Saúde - MAC | F96: Enfermeiro Diurno | G96: =IFERROR(VLOOKUP(F96,'Referencia PT'!D:F,2,FALSE),"-") -> Serviço Mensal | H96: PSF | I96: 45293 | J96: =IFERROR(VLOOKUP(F96,'Referencia PT'!D:F,3,FALSE),"0") -> 4950 | K96: 31 | L96: =IF(G96="SERVIÇO MENSAL",((J96/31)*K96),(J96*K96)) -> 4950
A97: 1 | B97: Tatielly de Oliveira Souza LTDA | C97: 59.959.862/0001-99 | D97: Tatielly de Oliveira Souza | E97: Secretaria de Saúde - APS/PAB | F97: Farmacêutico | G97: =IFERROR(VLOOKUP(F97,'Referencia PT'!D:F,2,FALSE),"-") -> Serviço Mensal | H97: PSF | I97: 45293 | J97: =IFERROR(VLOOKUP(F97,'Referencia PT'!D:F,3,FALSE),"0") -> 4770 | K97: =(31-10)+1 -> 22 | L97: =IF(G97="SERVIÇO MENSAL",((J97/31)*K97),(J97*K97)) -> 3385.1613
A98: 1 | B98: Vinicia - Clinica De Fisioterapia Ltda | C98: 48.624.416/0001-07 | D98: Vinicia Carolina Lia Halma Delmondes Soares | E98: Secretaria de Saúde - MAC | F98: Fisioterapeuta | G98: =IFERROR(VLOOKUP(F98,'Referencia PT'!D:F,2,FALSE),"-") -> Serviço Mensal | H98: PSF | I98: 45293 | J98: =IFERROR(VLOOKUP(F98,'Referencia PT'!D:F,3,FALSE),"0") -> 3862.16 | K98: 31 | L98: =IF(G98="SERVIÇO MENSAL",((J98/31)*K98),(J98*K98)) -> 3862.16
G99: =IFERROR(VLOOKUP(F99,'Referencia PT'!D:F,2,FALSE),"-") -> - | H99: PSF | I99: 45293 | J99: =IFERROR(VLOOKUP(F99,'Referencia PT'!D:F,3,FALSE),"0") -> 0 | L99: =IF(G99="SERVIÇO MENSAL",((J99/31)*K99),(J99*K99)) -> 0
A100: 38 | G100: =IFERROR(VLOOKUP(F100,'Referencia PT'!D:F,2,FALSE),"-") -> - | H100: PSF | I100: 45293 | J100: =IFERROR(VLOOKUP(F100,'Referencia PT'!D:F,3,FALSE),"0") -> 0 | L100: =IF(G100="SERVIÇO MENSAL",((J100/31)*K100),(J100*K100)) -> 0
A101: 40 | G101: =IFERROR(VLOOKUP(F101,'Referencia PT'!D:F,2,FALSE),"-") -> - | H101: PSF | I101: 45293 | J101: =IFERROR(VLOOKUP(F101,'Referencia PT'!D:F,3,FALSE),"0") -> 0 | L101: =IF(G101="SERVIÇO MENSAL",((J101/31)*K101),(J101*K101)) -> 0
A102: 40 | G102: =IFERROR(VLOOKUP(F102,'Referencia PT'!D:F,2,FALSE),"-") -> - | H102: PSF | I102: 45293 | J102: =IFERROR(VLOOKUP(F102,'Referencia PT'!D:F,3,FALSE),"0") -> 0 | L102: =IF(G102="SERVIÇO MENSAL",((J102/31)*K102),(J102*K102)) -> 0
A103: 42 | G103: =IFERROR(VLOOKUP(F103,'Referencia PT'!D:F,2,FALSE),"-") -> - | H103: PSF | I103: 45293 | J103: =IFERROR(VLOOKUP(F103,'Referencia PT'!D:F,3,FALSE),"0") -> 0 | L103: =IF(G103="SERVIÇO MENSAL",((J103/31)*K103),(J103*K103)) -> 0
A104: 42 | G104: =IFERROR(VLOOKUP(F104,'Referencia PT'!D:F,2,FALSE),"-") -> - | H104: PSF | I104: 45293 | J104: =IFERROR(VLOOKUP(F104,'Referencia PT'!D:F,3,FALSE),"0") -> 0 | L104: =IF(G104="SERVIÇO MENSAL",((J104/31)*K104),(J104*K104)) -> 0
A105: 42 | G105: =IFERROR(VLOOKUP(F105,'Referencia PT'!D:F,2,FALSE),"-") -> - | H105: PSF | I105: 45293 | J105: =IFERROR(VLOOKUP(F105,'Referencia PT'!D:F,3,FALSE),"0") -> 0 | L105: =IF(G105="SERVIÇO MENSAL",((J105/31)*K105),(J105*K105)) -> 0
...

Sheet TOTAL POR ATIVIDADE PT
C1: ='RESUMO FATURAMENTO'!C1 -> PREFEITURA MUNICIPAL DE DOM AQUINO/MT
C3: ='RESUMO FATURAMENTO'!C3 -> TERMO DE PARCERIA Nº 001/2026
C4: ='RESUMO FATURAMENTO'!C4 -> SECRETARIA MUNICIPAL DE SAÚDE
C5: ='RESUMO FATURAMENTO'!C5 -> TERMO DE PARCERIA Nº 001/2026
A7: RELATÓRIO SINTÉTICO POR ATIVIDADE
A9: ='RESUMO FATURAMENTO'!A9 -> OSCIP. ORGANIZAÇÃO DE SAÚDE SÃO BENTO
A11: ='RESUMO FATURAMENTO'!A11 -> PROJETO FORSAÚDE – Fortalecimento da Saúde Pública Municipal
A13: ='RESUMO FATURAMENTO'!A13 -> PERÍODO. AGOSTO DE 2026
A15: ='RESUMO FATURAMENTO'!A15 -> COMPETÊNCIA. 01 A 31 DE AGOSTO DE 2026
A17: ='RESUMO FATURAMENTO'!A20 -> 1.1 - CLT | I17: =SUM(I19:J30) -> 3855.42
A18: DESCRIÇÃO | H18: QTDADE | I18: VALOR
A19: Tecnico De Enfermagem | H19: =(COUNTIFS('DETALHAMENTO CLT'!D:D,A19))+(COUNTIFS('DETALHAMENTO PF'!C:C,A19)) -> 9 | I19: =((SUMIFS('DETALHAMENTO CLT'!Y:Y,'DETALHAMENTO CLT'!D:D,A19))+(SUMIFS('DETALHAMENTO PF'!U:U,'DETALHAMENTO PF'!C:C,A19))) -> 3855.42
A20: Tecnico Em Saude Bucal | H20: =(COUNTIFS('DETALHAMENTO CLT'!D:D,A20))+(COUNTIFS('DETALHAMENTO PF'!C:C,A20)) -> 0 | I20: =((SUMIFS('DETALHAMENTO CLT'!Y:Y,'DETALHAMENTO CLT'!D:D,A20))+(SUMIFS('DETALHAMENTO PF'!U:U,'DETALHAMENTO PF'!C:C,A20))) -> 0
A21: Tecnico Radiologia | H21: =(COUNTIFS('DETALHAMENTO CLT'!D:D,A21))+(COUNTIFS('DETALHAMENTO PF'!C:C,A21)) -> 0 | I21: =((SUMIFS('DETALHAMENTO CLT'!Y:Y,'DETALHAMENTO CLT'!D:D,A21))+(SUMIFS('DETALHAMENTO PF'!U:U,'DETALHAMENTO PF'!C:C,A21))) -> 0
A22: Vigia Noturno | H22: =(COUNTIFS('DETALHAMENTO CLT'!D:D,A22))+(COUNTIFS('DETALHAMENTO PF'!C:C,A22)) -> 0 | I22: =((SUMIFS('DETALHAMENTO CLT'!Y:Y,'DETALHAMENTO CLT'!D:D,A22))+(SUMIFS('DETALHAMENTO PF'!U:U,'DETALHAMENTO PF'!C:C,A22))) -> 0
H23: =(COUNTIFS('DETALHAMENTO CLT'!D:D,A23))+(COUNTIFS('DETALHAMENTO PF'!C:C,A23)) -> 1 | I23: =((SUMIFS('DETALHAMENTO CLT'!Y:Y,'DETALHAMENTO CLT'!D:D,A23))+(SUMIFS('DETALHAMENTO PF'!U:U,'DETALHAMENTO PF'!C:C,A23))) -> 0
H24: =(COUNTIFS('DETALHAMENTO CLT'!D:D,A24))+(COUNTIFS('DETALHAMENTO PF'!C:C,A24)) -> 1 | I24: =((SUMIFS('DETALHAMENTO CLT'!Y:Y,'DETALHAMENTO CLT'!D:D,A24))+(SUMIFS('DETALHAMENTO PF'!U:U,'DETALHAMENTO PF'!C:C,A24))) -> 0
H25: =(COUNTIFS('DETALHAMENTO CLT'!D:D,A25))+(COUNTIFS('DETALHAMENTO PF'!C:C,A25)) -> 1 | I25: =((SUMIFS('DETALHAMENTO CLT'!Y:Y,'DETALHAMENTO CLT'!D:D,A25))+(SUMIFS('DETALHAMENTO PF'!U:U,'DETALHAMENTO PF'!C:C,A25))) -> 0
H26: =(COUNTIFS('DETALHAMENTO CLT'!D:D,A26))+(COUNTIFS('DETALHAMENTO PF'!C:C,A26)) -> 1 | I26: =((SUMIFS('DETALHAMENTO CLT'!Y:Y,'DETALHAMENTO CLT'!D:D,A26))+(SUMIFS('DETALHAMENTO PF'!U:U,'DETALHAMENTO PF'!C:C,A26))) -> 0
H27: =(COUNTIFS('DETALHAMENTO CLT'!D:D,A27))+(COUNTIFS('DETALHAMENTO PF'!C:C,A27)) -> 1 | I27: =((SUMIFS('DETALHAMENTO CLT'!Y:Y,'DETALHAMENTO CLT'!D:D,A27))+(SUMIFS('DETALHAMENTO PF'!U:U,'DETALHAMENTO PF'!C:C,A27))) -> 0
H28: =(COUNTIFS('DETALHAMENTO CLT'!D:D,A28))+(COUNTIFS('DETALHAMENTO PF'!C:C,A28)) -> 1 | I28: =((SUMIFS('DETALHAMENTO CLT'!Y:Y,'DETALHAMENTO CLT'!D:D,A28))+(SUMIFS('DETALHAMENTO PF'!U:U,'DETALHAMENTO PF'!C:C,A28))) -> 0
H29: =(COUNTIFS('DETALHAMENTO CLT'!D:D,A29))+(COUNTIFS('DETALHAMENTO PF'!C:C,A29)) -> 1 | I29: =((SUMIFS('DETALHAMENTO CLT'!Y:Y,'DETALHAMENTO CLT'!D:D,A29))+(SUMIFS('DETALHAMENTO PF'!U:U,'DETALHAMENTO PF'!C:C,A29))) -> 0
H30: =(COUNTIFS('DETALHAMENTO CLT'!D:D,A30))+(COUNTIFS('DETALHAMENTO PF'!C:C,A30)) -> 1 | I30: =((SUMIFS('DETALHAMENTO CLT'!Y:Y,'DETALHAMENTO CLT'!D:D,A30))+(SUMIFS('DETALHAMENTO PF'!U:U,'DETALHAMENTO PF'!C:C,A30))) -> 0
A31: ='RESUMO FATURAMENTO'!A23 -> 0 | I31: =SUM(I33:J70) -> 0
A32: DESCRIÇÃO | G32: TIPO | H32: QTDADE | I32: VALOR
G33: =VLOOKUP(A33,'Referencia PT'!D:F,2,FALSE) -> #N/A | H33: =IF(G33="Serviço",(COUNTIFS('DETALHAMENTO PJ SAUDE'!F:F,A33)),(SUMIFS('DETALHAMENTO PJ SAUDE'!K:K,'DETALHAMENTO PJ SAUDE'!F:F,A33))) -> #N/A | I33: =SUMIFS('DETALHAMENTO PJ SAUDE'!L:L,'DETALHAMENTO PJ SAUDE'!F:F,A33) -> 0
G34: =VLOOKUP(A34,'Referencia PT'!D:F,2,FALSE) -> #N/A | H34: =IF(G34="Serviço",(COUNTIFS('DETALHAMENTO PJ SAUDE'!F:F,A34)),(SUMIFS('DETALHAMENTO PJ SAUDE'!K:K,'DETALHAMENTO PJ SAUDE'!F:F,A34))) -> #N/A | I34: =SUMIFS('DETALHAMENTO PJ SAUDE'!L:L,'DETALHAMENTO PJ SAUDE'!F:F,A34) -> 0
G35: =VLOOKUP(A35,'Referencia PT'!D:F,2,FALSE) -> #N/A | H35: =IF(G35="Serviço",(COUNTIFS('DETALHAMENTO PJ SAUDE'!F:F,A35)),(SUMIFS('DETALHAMENTO PJ SAUDE'!K:K,'DETALHAMENTO PJ SAUDE'!F:F,A35))) -> #N/A | I35: =SUMIFS('DETALHAMENTO PJ SAUDE'!L:L,'DETALHAMENTO PJ SAUDE'!F:F,A35) -> 0
G36: =VLOOKUP(A36,'Referencia PT'!D:F,2,FALSE) -> #N/A | H36: =IF(G36="Serviço",(COUNTIFS('DETALHAMENTO PJ SAUDE'!F:F,A36)),(SUMIFS('DETALHAMENTO PJ SAUDE'!K:K,'DETALHAMENTO PJ SAUDE'!F:F,A36))) -> #N/A | I36: =SUMIFS('DETALHAMENTO PJ SAUDE'!L:L,'DETALHAMENTO PJ SAUDE'!F:F,A36) -> 0
G37: =VLOOKUP(A37,'Referencia PT'!D:F,2,FALSE) -> #N/A | H37: =IF(G37="Serviço",(COUNTIFS('DETALHAMENTO PJ SAUDE'!F:F,A37)),(SUMIFS('DETALHAMENTO PJ SAUDE'!K:K,'DETALHAMENTO PJ SAUDE'!F:F,A37))) -> #N/A | I37: =SUMIFS('DETALHAMENTO PJ SAUDE'!L:L,'DETALHAMENTO PJ SAUDE'!F:F,A37) -> 0
G38: =VLOOKUP(A38,'Referencia PT'!D:F,2,FALSE) -> #N/A | H38: =IF(G38="Serviço",(COUNTIFS('DETALHAMENTO PJ SAUDE'!F:F,A38)),(SUMIFS('DETALHAMENTO PJ SAUDE'!K:K,'DETALHAMENTO PJ SAUDE'!F:F,A38))) -> #N/A | I38: =SUMIFS('DETALHAMENTO PJ SAUDE'!L:L,'DETALHAMENTO PJ SAUDE'!F:F,A38) -> 0
G39: =VLOOKUP(A39,'Referencia PT'!D:F,2,FALSE) -> #N/A | H39: =IF(G39="Serviço",(COUNTIFS('DETALHAMENTO PJ SAUDE'!F:F,A39)),(SUMIFS('DETALHAMENTO PJ SAUDE'!K:K,'DETALHAMENTO PJ SAUDE'!F:F,A39))) -> #N/A | I39: =SUMIFS('DETALHAMENTO PJ SAUDE'!L:L,'DETALHAMENTO PJ SAUDE'!F:F,A39) -> 0
G40: =VLOOKUP(A40,'Referencia PT'!D:F,2,FALSE) -> #N/A | H40: =IF(G40="Serviço",(COUNTIFS('DETALHAMENTO PJ SAUDE'!F:F,A40)),(SUMIFS('DETALHAMENTO PJ SAUDE'!K:K,'DETALHAMENTO PJ SAUDE'!F:F,A40))) -> #N/A | I40: =SUMIFS('DETALHAMENTO PJ SAUDE'!L:L,'DETALHAMENTO PJ SAUDE'!F:F,A40) -> 0
G41: =VLOOKUP(A41,'Referencia PT'!D:F,2,FALSE) -> #N/A | H41: =IF(G41="Serviço",(COUNTIFS('DETALHAMENTO PJ SAUDE'!F:F,A41)),(SUMIFS('DETALHAMENTO PJ SAUDE'!K:K,'DETALHAMENTO PJ SAUDE'!F:F,A41))) -> #N/A | I41: =SUMIFS('DETALHAMENTO PJ SAUDE'!L:L,'DETALHAMENTO PJ SAUDE'!F:F,A41) -> 0
G42: =VLOOKUP(A42,'Referencia PT'!D:F,2,FALSE) -> #N/A | H42: =IF(G42="Serviço",(COUNTIFS('DETALHAMENTO PJ SAUDE'!F:F,A42)),(SUMIFS('DETALHAMENTO PJ SAUDE'!K:K,'DETALHAMENTO PJ SAUDE'!F:F,A42))) -> #N/A | I42: =SUMIFS('DETALHAMENTO PJ SAUDE'!L:L,'DETALHAMENTO PJ SAUDE'!F:F,A42) -> 0
G43: =VLOOKUP(A43,'Referencia PT'!D:F,2,FALSE) -> #N/A | H43: =IF(G43="Serviço",(COUNTIFS('DETALHAMENTO PJ SAUDE'!F:F,A43)),(SUMIFS('DETALHAMENTO PJ SAUDE'!K:K,'DETALHAMENTO PJ SAUDE'!F:F,A43))) -> #N/A | I43: =SUMIFS('DETALHAMENTO PJ SAUDE'!L:L,'DETALHAMENTO PJ SAUDE'!F:F,A43) -> 0
G44: =VLOOKUP(A44,'Referencia PT'!D:F,2,FALSE) -> #N/A | H44: =IF(G44="Serviço",(COUNTIFS('DETALHAMENTO PJ SAUDE'!F:F,A44)),(SUMIFS('DETALHAMENTO PJ SAUDE'!K:K,'DETALHAMENTO PJ SAUDE'!F:F,A44))) -> #N/A | I44: =SUMIFS('DETALHAMENTO PJ SAUDE'!L:L,'DETALHAMENTO PJ SAUDE'!F:F,A44) -> 0
... G70: =VLOOKUP(A70,'Referencia PT'!D:F,2,FALSE) -> #N/A | H70: =IF(G70="Serviço",(COUNTIFS('DETALHAMENTO PJ SAUDE'!F:F,A70)),(SUMIFS('DETALHAMENTO PJ SAUDE'!K:K,'DETALHAMENTO PJ SAUDE'!F:F,A70))) -> #N/A | I70: =SUMIFS('DETALHAMENTO PJ SAUDE'!L:L,'DETALHAMENTO PJ SAUDE'!F:F,A70) -> 0

Sheet DESPESA ADM
C1: ='RESUMO FATURAMENTO'!C1 -> PREFEITURA MUNICIPAL DE DOM AQUINO/MT
C3: ='RESUMO FATURAMENTO'!C3 -> TERMO DE PARCERIA Nº 001/2026
C4: ='RESUMO FATURAMENTO'!C4 -> SECRETARIA MUNICIPAL DE SAÚDE
A6: 2. RELATÓRIO ANALÍTICO DESPESAS ADMINISTRATIVAS E OPERACIONAIS
A8: ='RESUMO FATURAMENTO'!A9 -> OSCIP. ORGANIZAÇÃO DE SAÚDE SÃO BENTO
A10: ='RESUMO FATURAMENTO'!A11 -> PROJETO FORSAÚDE – Fortalecimento da Saúde Pública Municipal
A12: ='RESUMO FATURAMENTO'!A13 -> PERÍODO. AGOSTO DE 2026
A14: ='RESUMO FATURAMENTO'!A15 -> COMPETÊNCIA. 01 A 31 DE AGOSTO DE 2026
A16: MEMÓRIA DE CÁLCULO PARA RATEIO DAS DESPESAS ADMINISTRATIVAS ENTRE AS SECRETARIAS DO TERMO DE PARCERIA Nº 001/2026
A17: SECRETARIA | E17: CUSTO DIRETO | H17: % RATEIO | J17: VALOR POR SECRETARIA
E18: CLT | F18: PJ | G18: TOTAL
A19: SECRETARIA MUNICIPAL DE ADMINISTRAÇÃO | E19: 0 | F19: 46571.01 | G19: =SUM(E19:F19) -> 46571.01 | H19: =G19/$G$29 -> 0.047162346 | J19: =IFERROR(($J$32*H19),"0") -> 5453.251 | M19: =G19+J19 -> 52024.261
A20: SECRETARIA MUNICIPAL DE AGRICULTURA | E20: 0 | F20: 9100 | G20: =SUM(E20:F20) -> 9100 | H20: =G20/$G$29 -> 0.0092155474 | J20: =IFERROR(($J$32*H20),"0") -> 1065.5681 | M20: =G20+J20 -> 10165.568
A21: SECRETARIA MUNICIPAL DE ASSISTÊNCIA SOCIAL E HABITAÇÃO | E21: 40850.08 | F21: 48185.51 | G21: =SUM(E21:F21) -> 89035.59 | H21: =G21/$G$29 -> 0.090166121 | J21: =IFERROR(($J$32*H21),"0") -> 10425.658 | M21: =G21+J21 -> 99461.248
A22: SECRETARIA MUNICIPAL DE CHEFIA DE GABINETE | E22: 0 | F22: 4500 | G22: =SUM(E22:F22) -> 4500 | H22: =G22/$G$29 -> 0.0045571388 | J22: =IFERROR(($J$32*H22),"0") -> 526.92929 | M22: =G22+J22 -> 5026.9293
A23: SECRETARIA MUNICIPAL DE CULTURA | E23: 0 | F23: 7200 | G23: =SUM(E23:F23) -> 7200 | H23: =G23/$G$29 -> 0.0072914221 | J23: =IFERROR(($J$32*H23),"0") -> 843.08687 | M23: =G23+J23 -> 8043.0869
A24: SECRETARIA MUNICIPAL DE EDUCAÇÃO | E24: 20541.14 | F24: 158586.72 | G24: =SUM(E24:F24) -> 179127.86 | H24: =G24/$G$29 -> 0.18140234 | J24: =IFERROR(($J$32*H24),"0") -> 20975.048 | M24: =G24+J24 -> 200102.91
A25: SECRETARIA MUNICIPAL DE ESPORTE E LAZER | E25: 5539.54 | F25: 12300 | G25: =SUM(E25:F25) -> 17839.54 | H25: =G25/$G$29 -> 0.018066058 | J25: =IFERROR(($J$32*H25),"0") -> 2088.928 | M25: =G25+J25 -> 19928.468
A26: SECRETARIA MUNICIPAL DE OBRAS PÚBLICAS E URBANISMO | E26: 28871.69 | F26: 173218.91 | G26: =SUM(E26:F26) -> 202090.6 | H26: =G26/$G$29 -> 0.20465665 | J26: =IFERROR(($J$32*H26),"0") -> 23663.879 | M26: =G26+J26 -> 225754.48
A27: SECRETARIA MUNICIPAL DE SAÚDE | E27: 79829.9 | F27: 339880.73 | G27: =SUM(E27:F27) -> 419710.63 | H27: =G27/$G$29 -> 0.42503991 | J27: =IFERROR(($J$32*H27),"0") -> 49146.183 | M27: =G27+J27 -> 468856.81
A28: DAE - DEPARTAMENTO DE ÁGUA E ESGOTO | E28: 0 | F28: 12286.46 | G28: =SUM(E28:F28) -> 12286.46 | H28: =G28/$G$29 -> 0.012442468 | J28: =IFERROR(($J$32*H28),"0") -> 1438.6879 | M28: =G28+J28 -> 13725.148
A29: TOTAL | E29: =SUM(E19:E28) -> 175632.35 | F29: =SUM(F19:F28) -> 811829.34 | G29: =SUM(G19:G28) -> 987461.69 | H29: =SUM(H19:I28) -> 1 | J29: =SUM(J19:K28) -> 115627.22 | M29: =G29+J29 -> 1103088.9
A32: DESPESAS ADMINISTRATIVAS E OPERACIONAIS TP Nº 001/2026 | J32: =SUM(J34:K38) -> 115627.22
A33: CLASSIFICAÇÃO DA DESPESA | F33: DOM AQUINO/MT | H33: RATEIO SEDE | J33: VALOR MENSAL
A34: Auditoria Independente (Em atendimento à Lei Federal nº 9.790/1999, ao Decreto nº 3.100/1999 e à Lei Estadual nº 11.082/2020, que estabelecem a obrigatoriedade de auditoria externa por profissional/empresa habilitada para análise da execução dos Termos de Parceria quando o valor pactuado for igual ou superior a R$ 600.000,00.) | F34: 2500 | H34: 0 | J34: =SUM(E34:I34) -> 2500
A35: Despesa com Imóvel (Despesas com Locação de Imóvel, Fornecimento de Água e Energia Elétrica, Internet/Telefone, Manutenção Predial e Afins) | F35: 0 | H35: 8000 | J35: =SUM(E35:I35) -> 8000
A36: Despesas Bancárias (Despesas com Tarifa Manutenção Mensal, Tarifas Transferências Bancárias e Afins) | F36: 400 | H36: 200 | J36: =SUM(E36:I36) -> 600
A37: Despesas Pessoa Física e Jurídica (Despesas com Honorários Advocatícios e Contábeis, Contratação de Prestadores e/ou Profissionais nas Áreas: Administrativa, Financeira, Projetos, Faturamento, TI, Verificação Independente, Gestão, Locação de Veículo(s) e Impressora(s), Diária(s), Deslocamento e Afins) | F37: 73727.22 | H37: 30000 | J37: =SUM(E37:I37) -> 103727.22
A38: Materiais de Consumo e Expediente (Despesa com Materiais de Uso na Rotina Administrativa, Limpeza, Copa e Afins) | F38: 500 | H38: 300 | J38: =SUM(E38:I38) -> 800

Sheet Referencia PT
C6: SECRETARIA | D6: ATIVIDADE | E6: TIPO | F6: REMUNERAÇÃO
C7: Sec Saude | D7: Acompanhamento de Paciente | E7: Serviço Mensal | F7: 2500
C8: Sec Saude | D8: Agente de Conservação e Limpeza II | E8: Serviço Mensal | F8: 1800
C9: Sec Saude | D9: Assistente Social | E9: Serviço Mensal | F9: 3300
C10: Sec Saude | D10: Auxiliar de Saúde Bucal | E10: Serviço Mensal | F10: 2400
C11: Sec Saude | D11: Bioquímico I | E11: Serviço Mensal | F11: 5112
C12: Sec Saude | D12: Controlador de Frota | E12: Serviço Mensal | F12: 4000
C13: Sec Saude | D13: Controlador de Frota - Plantão | E13: Demanda | F13: =4000/31 -> 129.03226
C14: Sec Saude | D14: Coordenador Administrativo | E14: Serviço Mensal | F14: 5200
C15: Sec Saude | D15: Coordenador de Unidade de Saúde | E15: Serviço Mensal | F15: 6000
C16: Sec Saude | D16: Dentista | E16: Serviço Mensal | F16: 4770
C17: Sec Saude | D17: Educador Físico I | E17: Serviço Mensal | F17: 3300
C18: Sec Saude | D18: Enfermeiro | E18: Serviço Mensal | F18: 4770
C19: Sec Saude | D19: Enfermeiro Diurno | E19: Serviço Mensal | F19: 4950
C20: Sec Saude | D20: Enfermeiro Noturno | E20: Serviço Mensal | F20: 5200
C21: Sec Saude | D21: Farmacêutico | E21: Serviço Mensal | F21: 4770
C22: Sec Saude | D22: Fisioterapeuta | E22: Serviço Mensal | F22: 3862.16
C23: Sec Saude | D23: Médico Clínico – Plantão 12h | E23: Demanda | F23: 1400
C24: Sec Saude | D24: Médico Clínico Geral | E24: Serviço Mensal | F24: 19500
C25: Sec Saude | D25: Motorista I | E25: Serviço Mensal | F25: 2400
... C33: Sec Saude | D33: Técnico Administrativo II | E33: Serviço Mensal | F33: 2534.82
D34: Motorista - Plantão | E34: Demanda | F34: 87
D35: Coordernador Administrativo - Plantão | E35: Demanda | F35: 190
D36: Técnico Administrativo II - Plantão | E36: Demanda | F36: 87
D37: Enfermeiro - Plantão | E37: Demanda | F37: =4770/30 -> 159
D38: Serviços Gerais - Plantão | E38: Demanda | F38: =1800/30 -> 60
D39: Recepcionista - Plantão | E39: Demanda | F39: 67
